Metadata-Version: 2.1
Name: django-http-etag-view
Version: 2020.7.1
Summary: Django http Etag header view mixin
Home-page: https://github.com/andrewp-as-is/django-http-etag-view.py
License: Unlicense
Keywords: django Etag header view
Platform: UNKNOWN
Classifier: Framework :: Django
Classifier: License :: Public Domain
Classifier: Operating System :: OS Independent
Classifier: Programming Language :: Python :: 3
